LICENSE
README.md
pyproject.toml
runscript/__init__.py
runscript/cli.py
runscript/lock.py
runscript/py.typed
runscript.egg-info/PKG-INFO
runscript.egg-info/SOURCES.txt
runscript.egg-info/dependency_links.txt
runscript.egg-info/entry_points.txt
runscript.egg-info/requires.txt
runscript.egg-info/top_level.txt
tests/test_runscript.py