Metadata-Version: 2.1
Name: runscript
Version: 0.3.5
Summary: Simple script launcher
Author-email: Gregory Petukhov <lorien@lorien.name>
License: The MIT License (MIT)
Project-URL: homepage, http://github.com/lorien/runscript
Keywords: script,cli,utility,run,launch,task
Classifier: Programming Language :: Python
Classifier: Programming Language :: Python :: 3
Classifier: Programming Language :: Python :: 3.7
Classifier: Programming Language :: Python :: 3.8
Classifier: Programming Language :: Python :: 3.9
Classifier: Programming Language :: Python :: 3.10
Classifier: License :: OSI Approved :: MIT License
Classifier: Development Status :: 4 - Beta
Classifier: Environment :: Console
Classifier: Intended Audience :: Developers
Classifier: Operating System :: OS Independent
Classifier: Topic :: Software Development :: Libraries :: Python Modules
Classifier: Topic :: Utilities
Classifier: Typing :: Typed
Requires-Python: >=3.7
Provides-Extra: test
License-File: LICENSE
